leetcode_local_tester/__init__.py
leetcode_local_tester/creator/__init__.py
leetcode_local_tester/creator/cpp_creator.py
leetcode_local_tester/creator/creator.py
leetcode_local_tester/creator/python3_creator.py
leetcode_local_tester/helper/__init__.py
leetcode_local_tester/helper/fetch.py
leetcode_local_tester/helper/handler.py
leetcode_local_tester/helper/utils.py
leetcode_local_tester/main.py
leetcode_local_tester/model/__init__.py
leetcode_local_tester/model/config.py
leetcode_local_tester/model/contest.py
leetcode_local_tester/model/problem.py
leetcode_local_tester/parsers/__init__.py
leetcode_local_tester/parsers/parser.py
leetcode_local_tester/parsers/problem_parser.py
leetcode_local_tester/parsers/season_contest_parser.py
leetcode_local_tester/parsers/utils.py
leetcode_local_tester/parsers/weekly_contest_parser.py
leetcode_local_tester/template/cpp/.clang-format
leetcode_local_tester/template/cpp/main.cpp
leetcode_local_tester/template/cpp/method_main.cpp
leetcode_local_tester/template/cpp/solve.h
leetcode_local_tester/template/python3/main.py
leetcode_local_tester/template/python3/method_main.py
leetcode_local_tester/template/python3/solution.py
leetcode_local_tester/template/utils/__init__.py
leetcode_local_tester/template/utils/cpp/help.hpp
leetcode_local_tester/template/utils/python3/help.py
leetcode_local_tester/template/utils/python3/requirements.txt
leetcode_local_tester-0.6.0.dist-info/entry_points.txt
leetcode_local_tester-0.6.0.dist-info/LICENSE
leetcode_local_tester-0.6.0.dist-info/WHEEL
leetcode_local_tester-0.6.0.dist-info/METADATA
leetcode_local_tester-0.6.0.dist-info/RECORD
