Metadata-Version: 2.1
Name: leetcode-local-tester
Version: 0.6.0
Summary: 
License: MIT
Author: shen
Author-email: goodstudyQAQ@163.com
Requires-Python: >=3.7,<4.0
Classifier: License :: OSI Approved :: MIT License
Classifier: Programming Language :: Python :: 3
Classifier: Programming Language :: Python :: 3.7
Classifier: Programming Language :: Python :: 3.8
Classifier: Programming Language :: Python :: 3.9
Classifier: Programming Language :: Python :: 3.10
Classifier: Programming Language :: Python :: 3.11
Requires-Dist: alive-progress (>=3.1.4,<4.0.0)
Requires-Dist: beautifulsoup4 (==4.9.1)
Requires-Dist: clang-format (>=16.0.6,<17.0.0)
Requires-Dist: click (==8.1.4)
Requires-Dist: dacite (==1.8.0)
Requires-Dist: html5lib (==1.1)
Requires-Dist: requests (>=2.31.0,<3.0.0)
